LSExcelParser/__init__.py
LSExcelParser-1.1.0.dist-info/METADATA
LSExcelParser-1.1.0.dist-info/WHEEL
LSExcelParser-1.1.0.dist-info/top_level.txt
LSExcelParser-1.1.0.dist-info/RECORD
