Metadata-Version: 2.1
Name: LSExcelParser
Version: 1.1.0
Summary: UNKNOWN
Home-page: https://github.com/EasonNothingToSing/LSExcelParser
Author: Eason wang
Author-email: EasonNothingToSing@outlook.com
License: MIT
Platform: UNKNOWN
Classifier: License :: OSI Approved :: MIT License
Classifier: Programming Language :: Python
Classifier: Programming Language :: Python :: 3
Classifier: Programming Language :: Python :: 3.6
Classifier: Programming Language :: Python :: Implementation :: CPython
Classifier: Programming Language :: Python :: Implementation :: PyPy
Requires-Python: >=3.6.0
Requires-Dist: xlrd
